lrabbit_scrapy/__init__.py
lrabbit_scrapy/__main__.py
lrabbit_scrapy/asy_crawl.py
lrabbit_scrapy/asynico_basespider.py
lrabbit_scrapy/command.py
lrabbit_scrapy/config.py
lrabbit_scrapy/spider.py
lrabbit_scrapy/template_crawl.py
lrabbit_scrapy/all_excepiton/__init__.py
lrabbit_scrapy/android/__init__.py
lrabbit_scrapy/android/sslbypass.py
lrabbit_scrapy/android/sslpass.js
lrabbit_scrapy/asynico_utils/__init__.py
lrabbit_scrapy/common_utils/__init__.py
lrabbit_scrapy/common_utils/all_in_one.py
lrabbit_scrapy/common_utils/config_helper.py
lrabbit_scrapy/common_utils/mysql_helper.py
lrabbit_scrapy/common_utils/network_helper.py
lrabbit_scrapy/common_utils/print_log_helper.py
lrabbit_scrapy/common_utils/redis_helper.py
lrabbit_scrapy-2.0.8.dist-info/LICENSE
lrabbit_scrapy-2.0.8.dist-info/LICENSE.rst
lrabbit_scrapy-2.0.8.dist-info/METADATA
lrabbit_scrapy-2.0.8.dist-info/WHEEL
lrabbit_scrapy-2.0.8.dist-info/top_level.txt
lrabbit_scrapy-2.0.8.dist-info/RECORD
