Metadata-Version: 2.1
Name: lrabbit-scrapy
Version: 2.0.8
Summary: this is a small spider,you can easy running. When you often need to crawl a single site, you can reduce some repeated code every time, using this small framework you can quickly crawl data into a file or database.
Home-page: https://github.com/litter-rabbit/lrabbit_scrapy
Author: lrabbit
Author-email: 709343607@qq.com
License: UNKNOWN
Project-URL: Bug Tracker, https://github.com/litter-rabbit/lrabbit_scrapy/issues
Platform: UNKNOWN
Classifier: Programming Language :: Python :: 3
Classifier: License :: OSI Approved :: MIT License
Classifier: Operating System :: OS Independent
Requires-Python: >=3.6.8
License-File: LICENSE
License-File: LICENSE.rst
Requires-Dist: parsel (==1.6.0)
Requires-Dist: requests (>=2.26.0)
Requires-Dist: PyMySQL (>=0.9.3)
Requires-Dist: redispy (>=3.0.0)
Requires-Dist: frida (>=15.0.0)
Requires-Dist: frida-tools (>=10.4.1)
